xrdphase/__init__.py
xrdphase/_version.py
xrdphase/free_pdf.py
xrdphase/phase_id_functions.py
xrdphase/phase_id_script.py
xrdphase/training_NN_funcs.py
xrdphase/tests/__init__.py
xrdphase/tests/conftest.py
xrdphase/tests/test_find_phase.py
xrdphase-0.0.1a1.dist-info/AUTHORS.rst
xrdphase-0.0.1a1.dist-info/LICENSE
xrdphase-0.0.1a1.dist-info/METADATA
xrdphase-0.0.1a1.dist-info/WHEEL
xrdphase-0.0.1a1.dist-info/entry_points.txt
xrdphase-0.0.1a1.dist-info/top_level.txt
xrdphase-0.0.1a1.dist-info/RECORD
