Metadata-Version: 2.1
Name: xrdphase
Version: 0.0.1a1
Summary: Python package for doing science.
Home-page: https://github.com/gwbischof/xrdphase
Author: Brookhaven National Lab
Author-email: gbischof@bnl.gov
License: BSD (3-clause)
Platform: UNKNOWN
Classifier: Development Status :: 2 - Pre-Alpha
Classifier: Natural Language :: English
Classifier: Programming Language :: Python :: 3
Requires-Python: >=3.6
